main.py
setup.py
LargeBatchCTR.egg-info/PKG-INFO
LargeBatchCTR.egg-info/SOURCES.txt
LargeBatchCTR.egg-info/dependency_links.txt
LargeBatchCTR.egg-info/requires.txt
LargeBatchCTR.egg-info/top_level.txt